wmlog/__init__.py
wmlog/cli.py
wmlog/decorators.py
wmlog/formatters/__init__.py
wmlog/formatters/structured.py
wmlog/handlers/__init__.py
wmlog/handlers/custom.py
wmlog/logging/__init__.py
wmlog/logging/core.py
wmlog/mqtt/__init__.py
wmlog/mqtt/broadcaster.py
wmlog-1.0.4.dist-info/licenses/LICENSE
wmlog-1.0.4.dist-info/METADATA
wmlog-1.0.4.dist-info/WHEEL
wmlog-1.0.4.dist-info/entry_points.txt
wmlog-1.0.4.dist-info/top_level.txt
wmlog-1.0.4.dist-info/RECORD
