Metadata-Version: 2.4
Name: wmlog
Version: 1.0.4
Summary: Centralized Structured Logging for Microservices
Home-page: https://github.com/tom-sapletta-com/wmlog
Author: Tom Sapletta
Author-email: info@softreck.dev
License: Apache-2.0
Project-URL: Documentation, https://wml.softreck.dev/docs
Project-URL: Source, https://github.com/wml-org/wml
Project-URL: Tracker, https://github.com/wml-org/wml/issues
Keywords: logging,websocket,mqtt,distributed,microservices,structured-logging,real-time,monitoring,observability,asyncio,broadcasting,centralized-logging
Classifier: Development Status :: 4 - Beta
Classifier: Intended Audience :: Developers
Classifier: Intended Audience :: System Administrators
Classifier: License :: OSI Approved :: Apache Software License
Classifier: Operating System :: OS Independent
Classifier: Programming Language :: Python :: 3
Classifier: Programming Language :: Python :: 3.8
Classifier: Programming Language :: Python :: 3.9
Classifier: Programming Language :: Python :: 3.10
Classifier: Programming Language :: Python :: 3.11
Classifier: Programming Language :: Python :: 3.12
Classifier: Topic :: System :: Logging
Classifier: Topic :: System :: Monitoring
Classifier: Topic :: Software Development :: Libraries :: Python Modules
Classifier: Topic :: Internet :: WWW/HTTP :: HTTP Servers
Classifier: Framework :: AsyncIO
Requires-Python: >=3.8
License-File: LICENSE
Requires-Dist: structlog>=23.1.0
Requires-Dist: rich>=13.0.0
Requires-Dist: aiohttp>=3.8.0
Requires-Dist: paho-mqtt>=1.6.0
Requires-Dist: websockets>=11.0.0
Requires-Dist: python-dotenv>=1.0.0
Requires-Dist: PyYAML>=6.0
Requires-Dist: click>=8.0.0
Provides-Extra: redis
Requires-Dist: redis>=4.3.0; extra == "redis"
Provides-Extra: influxdb
Requires-Dist: influxdb-client>=1.36.0; extra == "influxdb"
Provides-Extra: elasticsearch
Requires-Dist: elasticsearch>=8.0.0; extra == "elasticsearch"
Provides-Extra: kafka
Requires-Dist: kafka-python>=2.0.0; extra == "kafka"
Provides-Extra: monitoring
Requires-Dist: prometheus-client>=0.16.0; extra == "monitoring"
Requires-Dist: grafana-api>=1.0.3; extra == "monitoring"
Provides-Extra: development
Requires-Dist: pytest>=7.0.0; extra == "development"
Requires-Dist: pytest-asyncio>=0.21.0; extra == "development"
Requires-Dist: black>=22.0.0; extra == "development"
Provides-Extra: all
Requires-Dist: redis>=4.3.0; extra == "all"
Requires-Dist: influxdb-client>=1.36.0; extra == "all"
Requires-Dist: elasticsearch>=8.0.0; extra == "all"
Requires-Dist: kafka-python>=2.0.0; extra == "all"
Requires-Dist: prometheus-client>=0.16.0; extra == "all"
Requires-Dist: pytest>=7.0.0; extra == "all"
Requires-Dist: pytest-asyncio>=0.21.0; extra == "all"
Dynamic: author
Dynamic: author-email
Dynamic: classifier
Dynamic: description
Dynamic: description-content-type
Dynamic: home-page
Dynamic: keywords
Dynamic: license
Dynamic: license-file
Dynamic: project-url
Dynamic: provides-extra
Dynamic: requires-dist
Dynamic: requires-python
Dynamic: summary
